alert_me/__init__.py
alert_me/__main__.py
alert_me/_version.py
alert_me/alert_me.py
alert_me/config.py
alert_me/plugin.py
alert_me/plugins/__init__.py
alert_me/plugins/email.py
alert_me/plugins/telegram.py
alert_me/plugins/url.py
python_alert-0.1.0.dist-info/LICENSE
python_alert-0.1.0.dist-info/METADATA
python_alert-0.1.0.dist-info/WHEEL
python_alert-0.1.0.dist-info/entry_points.txt
python_alert-0.1.0.dist-info/top_level.txt
python_alert-0.1.0.dist-info/RECORD
