Metadata-Version: 2.1
Name: python-alert
Version: 0.1.0
Summary: Multi-Platform Python tool to send notifications to your devices
Home-page: https://github.com/NeverMendel/alert-me
Author: Davide Cazzin
Author-email: 28535750+NeverMendel@users.noreply.github.com
License: MIT
Keywords: python-alert,alert-me,notify-me,email,notification
Classifier: Programming Language :: Python :: 3
Classifier: Programming Language :: Python :: 3.9
Classifier: License :: OSI Approved :: MIT License
Classifier: Operating System :: OS Independent
Requires-Python: >=3.8
License-File: LICENSE
Requires-Dist: configparser
Requires-Dist: requests
